label_explorer_cli/__init__.py
label_explorer_cli/label_cls_parse.py
label_explorer_cli/label_explorer.py
label_explorer_cli/label_merge.py
label_explorer_cli/label_studio_parse.py
label_explorer_cli/utils/time_format.py
label_explorer-0.0.2.dist-info/LICENSE
label_explorer-0.0.2.dist-info/METADATA
label_explorer-0.0.2.dist-info/WHEEL
label_explorer-0.0.2.dist-info/entry_points.txt
label_explorer-0.0.2.dist-info/top_level.txt
label_explorer-0.0.2.dist-info/RECORD
