Metadata-Version: 2.1
Name: label-explorer
Version: 0.0.2
Summary: 基于 Electron 的 YOLO 标签分析与整合工具 (Python CLI版)
Author: 曾逸夫 Zeng Yifu, 邓乙华 Deng Yihua
Maintainer: 曾逸夫 Zeng Yifu, 邓乙华 Deng Yihua
License: GPL-3.0
Project-URL: Bug Reports, https://gitee.com/intelligence-vision/label-explorer/issues
Project-URL: Funding, https://gitee.com/intelligence-vision
Project-URL: Source, https://gitee.com/intelligence-vision/label-explorer
Keywords: Electron,YOLO,labels,images
Requires-Python: >=3.8
License-File: LICENSE
Requires-Dist: opencv-python >=4.9.0.80
Requires-Dist: click >=8.1.7
Requires-Dist: pyscript >=0.2.5
Requires-Dist: black >=24.1.1
Requires-Dist: isort >=5.13.2
Requires-Dist: mdformat >=0.7.17
Requires-Dist: rich ==12.6.0
